bert_local/__init__.py
bert_local/bert.py
bert_local-0.0.12.dist-info/METADATA
bert_local-0.0.12.dist-info/WHEEL
bert_local-0.0.12.dist-info/top_level.txt
bert_local-0.0.12.dist-info/RECORD
